biql/__init__.py
biql/__main__.py
biql/ast_nodes.py
biql/cli.py
biql/dataset.py
biql/evaluator.py
biql/formatter.py
biql/lexer.py
biql/parser.py
biql/query.py
biql/utils.py
biql-0.3.0.dist-info/licenses/LICENSE
biql-0.3.0.dist-info/METADATA
biql-0.3.0.dist-info/WHEEL
biql-0.3.0.dist-info/entry_points.txt
biql-0.3.0.dist-info/top_level.txt
biql-0.3.0.dist-info/RECORD
