Metadata-Version: 2.4
Name: biql
Version: 0.3.0
Summary: BIDS Query Language - A powerful SQL-like query language for BIDS neuroimaging datasets
Home-page: https://github.com/astewartau/biql
Author: Ashley Stewart
License: MIT License
Project-URL: Homepage, https://github.com/astewartau/biql
Project-URL: Documentation, https://astewartau.github.io/biql/
Project-URL: Repository, https://github.com/astewartau/biql
Project-URL: Bug Reports, https://github.com/astewartau/biql/issues
Keywords: bids,neuroimaging,query,language,sql,medical-imaging,neuroscience
Classifier: Development Status :: 3 - Alpha
Classifier: Intended Audience :: Science/Research
Classifier: Intended Audience :: Developers
Classifier: Topic :: Scientific/Engineering
Classifier: Topic :: Scientific/Engineering :: Medical Science Apps.
Classifier: Topic :: Software Development :: Libraries :: Python Modules
Classifier: License :: OSI Approved :: MIT License
Classifier: Programming Language :: Python :: 3
Classifier: Programming Language :: Python :: 3.8
Classifier: Programming Language :: Python :: 3.9
Classifier: Programming Language :: Python :: 3.10
Classifier: Programming Language :: Python :: 3.11
Classifier: Programming Language :: Python :: 3.12
Classifier: Operating System :: OS Independent
Requires-Python: >=3.8
License-File: LICENSE
Requires-Dist: psutil
Requires-Dist: pandas
Requires-Dist: tabulate
Provides-Extra: dev
Requires-Dist: pytest>=6.0; extra == "dev"
Requires-Dist: pytest-cov; extra == "dev"
Requires-Dist: black; extra == "dev"
Requires-Dist: isort; extra == "dev"
Requires-Dist: flake8; extra == "dev"
Requires-Dist: pre-commit; extra == "dev"
Provides-Extra: test
Requires-Dist: pytest>=6.0; extra == "test"
Requires-Dist: pytest-cov; extra == "test"
Dynamic: home-page
Dynamic: license-file
Dynamic: requires-python
